sortabletable/__init__.py
sortabletable/cms_plugins.py
sortabletable/models.py
sortabletable/locale/de/LC_MESSAGES/django.mo
sortabletable/locale/de/LC_MESSAGES/django.po
sortabletable/locale/en/LC_MESSAGES/django.mo
sortabletable/locale/en/LC_MESSAGES/django.po
sortabletable/migrations/0001_initial.py
sortabletable/migrations/__init__.py
sortabletable/static/sortabletable/css/main.css
sortabletable/static/sortabletable/js/main.js
sortabletable/templates/sortabletable/render_table.html
sortabletable-0.0.15.dist-info/LICENSE
sortabletable-0.0.15.dist-info/METADATA
sortabletable-0.0.15.dist-info/WHEEL
sortabletable-0.0.15.dist-info/top_level.txt
sortabletable-0.0.15.dist-info/RECORD
